setup.cfg
setup.py
txanalytics/__init__.py
txanalytics/googleanalytics.py
txanalytics.egg-info/PKG-INFO
txanalytics.egg-info/SOURCES.txt
txanalytics.egg-info/dependency_links.txt
txanalytics.egg-info/requires.txt
txanalytics.egg-info/top_level.txt