Metadata-Version: 1.1
Name: txanalytics
Version: 0.1.4
Summary: A Twisted based client for Google Analytics Measurement Protocol
Home-page: https://gitlab.com/syncmeapp/txanalytics
Author: Yehuda Deutsch
Author-email: yeh@uda.co.il
License: MIT
Download-URL: https://gitlab.com/syncmeapp/txanalytics/repository/archive.tar.gz?ref=master
Keywords: analytics
Platform: any
Classifier: Development Status :: 3 - Alpha
Classifier: Framework :: Twisted
Classifier: Intended Audience :: Developers
Classifier: License :: OSI Approved :: MIT License
Classifier: Operating System :: OS Independent
Classifier: Programming Language :: Python
Classifier: Programming Language :: Python :: 2.7
Classifier: Programming Language :: Python :: 3
Classifier: Programming Language :: Python :: 3.6
Classifier: Topic :: Software Development :: Libraries :: Python Modules
